django_grpc_framework/__init__.py
django_grpc_framework/apps.py
django_grpc_framework/generics.py
django_grpc_framework/mixins.py
django_grpc_framework/proto_serializers.py
django_grpc_framework/services.py
django_grpc_framework/settings.py
django_grpc_framework/signals.py
django_grpc_framework/test.py
django_grpc_framework/management/__init__.py
django_grpc_framework/management/commands/__init__.py
django_grpc_framework/management/commands/generateproto.py
django_grpc_framework/management/commands/grpcrunserver.py
django_grpc_framework/protobuf/__init__.py
django_grpc_framework/protobuf/generators.py
django_grpc_framework/protobuf/json_format.py
django_grpc_framework/utils/__init__.py
django_grpc_framework/utils/model_meta.py
djangogrpcframework-0.2.1.dist-info/LICENSE
djangogrpcframework-0.2.1.dist-info/METADATA
djangogrpcframework-0.2.1.dist-info/WHEEL
djangogrpcframework-0.2.1.dist-info/top_level.txt
djangogrpcframework-0.2.1.dist-info/RECORD
